setup.py
django_roa/__init__.py
django_roa/models.py
django_roa.egg-info/PKG-INFO
django_roa.egg-info/SOURCES.txt
django_roa.egg-info/dependency_links.txt
django_roa.egg-info/top_level.txt
django_roa/db/__init__.py
django_roa/db/admin.py
django_roa/db/exceptions.py
django_roa/db/managers.py
django_roa/db/models.py
django_roa/db/query.py
django_roa/management/__init__.py
django_roa/management/commands/__init__.py
django_roa/management/commands/inspectresources.py
django_roa/remoteauth/__init__.py
django_roa/remoteauth/backends.py
django_roa/remoteauth/models.py
examples/__init__.py
examples/django_roa_client/__init__.py
examples/django_roa_client/admin.py
examples/django_roa_client/forms.py
examples/django_roa_client/manage.py
examples/django_roa_client/models.py
examples/django_roa_client/serializers.py
examples/django_roa_client/settings.py
examples/django_roa_client/tests.py
examples/django_roa_client/urls.py
examples/django_roa_client/views.py
examples/django_roa_server/__init__.py
examples/django_roa_server/emitters.py
examples/django_roa_server/handlers.py
examples/django_roa_server/manage.py
examples/django_roa_server/models.py
examples/django_roa_server/settings.py
examples/django_roa_server/urls.py
examples/twitter_roa/__init__.py
examples/twitter_roa/admin.py
examples/twitter_roa/manage.py
examples/twitter_roa/models.py
examples/twitter_roa/serializers.py
examples/twitter_roa/settings.py
examples/twitter_roa/urls.py