Metadata-Version: 1.0
Name: django-roa
Version: 1.7
Summary: Turn your models into remote resources that you can access through Django's ORM.
Home-page: http://code.welldev.org/django-roa/wiki/Home
Author: David Larlet
Author-email: david@larlet.fr
License: BSD
Download-URL: http://code.welldev.org/django-roa/downloads/
Platform: UNKNOWN
Classifier: Development Status :: 4 - Beta
Classifier: Environment :: Web Environment
Classifier: Framework :: Django
Classifier: Intended Audience :: Developers
Classifier: License :: OSI Approved :: BSD License
Classifier: Operating System :: OS Independent
Classifier: Programming Language :: Python
Classifier: Topic :: Internet :: WWW/HTTP
